epic_fourier/__init__.py
epic_fourier/epic_fourier.py
epic_fourier-0.1.2.1.dist-info/METADATA
epic_fourier-0.1.2.1.dist-info/WHEEL
epic_fourier-0.1.2.1.dist-info/top_level.txt
epic_fourier-0.1.2.1.dist-info/RECORD
