Metadata-Version: 2.1
Name: epic_fourier
Version: 0.1.2.1
Summary: A library for computing Fourier Series made for Physics Students!
Home-page: https://github.com/KingL0ui5/FSeries-Python-Library
Author: Louis Liu
Author-email: LiuLouis1@gmail.com
License: MIT
Classifier: Programming Language :: Python :: 3
Classifier: License :: OSI Approved :: MIT License
Classifier: Operating System :: OS Independent
Requires-Python: >=3.6
Requires-Dist: numpy
Requires-Dist: scipy
Requires-Dist: pandas
